nodestream_plugin_splunk/__init__.py
nodestream_plugin_splunk/plugin.py
nodestream_plugin_splunk/splunk.yaml
nodestream_plugin_splunk/splunk_extractor.py
nodestream_plugin_splunk-0.2.0.dist-info/METADATA
nodestream_plugin_splunk-0.2.0.dist-info/WHEEL
nodestream_plugin_splunk-0.2.0.dist-info/entry_points.txt
nodestream_plugin_splunk-0.2.0.dist-info/RECORD
