Metadata-Version: 2.1
Name: nodestream-plugin-splunk
Version: 0.2.0
Summary: 
Author: Your Name
Author-email: you@example.com
Requires-Python: >=3.12,<4.0
Classifier: Programming Language :: Python :: 3
Classifier: Programming Language :: Python :: 3.12
Requires-Dist: nodestream (>=0.12.3,<0.13.0)
Requires-Dist: splunk-sdk (>=2.0.1,<3.0.0)
